{
  "seed": 0,
  "device": "auto",
  "experiment": {
    "name": "lunarlander_rr32_srsac",
    "output_root": "runs"
  },
  "env": {
    "id": "LunarLanderContinuous-v3",
    "kwargs": {}
  },
  "algorithm": {
    "actor_lr": 0.0003,
    "critic_lr": 0.0003,
    "alpha_lr": 0.0003,
    "hidden_dims": [256, 256],
    "discount": 0.99,
    "tau": 0.005,
    "init_temperature": 1.0,
    "target_entropy": null,
    "learnable_temperature": true,
    "log_std_min": -5.0,
    "log_std_max": 2.0,
    "replay_size": 200000,
    "updates_per_step": 32,
    "resets": true,
    "reset_interval_updates": 2560000
  },
  "train": {
    "total_env_steps": 100000,
    "start_steps": 2000,
    "start_training_after": 2000,
    "batch_size": 256,
    "eval_every": 5000,
    "eval_episodes": 5,
    "video_episodes": 1
  }
}
